openapiclient/__init__.py
openapiclient/client.py
openapi_httpx_client-0.4.2.dist-info/METADATA
openapi_httpx_client-0.4.2.dist-info/WHEEL
openapi_httpx_client-0.4.2.dist-info/top_level.txt
openapi_httpx_client-0.4.2.dist-info/RECORD
