Metadata-Version: 2.1
Name: openapi-httpx-client
Version: 0.4.2
Summary: A Python client for OpenAPI specifications using httpx
Home-page: https://github.com/lloydzhou/openapiclient
Author: lloydzhou
Author-email: lloydzhou@qq.com
License: UNKNOWN
Platform: UNKNOWN
Classifier: Programming Language :: Python :: 3
Classifier: License :: OSI Approved :: MIT License
Classifier: Operating System :: OS Independent
Requires-Python: >=3.7
Requires-Dist: httpx >=0.23.0
Requires-Dist: pyyaml >=6.0
